example/adder.v
`timescale 10ns / 1ns

module adder (
	input  [7:0] operand0,
	input  [7:0] operand1,
	output reg [7:0] result
);

	/*TODO: Please add your logic design here*/
	always @ (*)
	begin
		result = operand0 + operand1;
	end

	initial begin
		#20
		$display("I am an iKun!\n");
	end

endmodule

example/adder_tb.v
`timescale 10ns / 1ns

module adder_test_g();
        reg [7:0] op1, op2;
        wire [7:0] sum;

        adder a1 (
                .operand0(op1),
                .operand1(op2),
                .result(sum)
        );

        initial
        begin
                op1 = 8'd0;
                op2 = 8'd0;
                #1000
                $display("CAIXUKUN!!!\n");
                $finish;
        end

        always #20
        begin

                op1 = {$random} % 256;
                op2 = {$random} % 256;

        end

        initial
        begin            
                $dumpfile("adder_tb.vcd");        //生成的vcd文件名称
                $dumpvars(0, adder_test_g);    		//tb模块名称
        end
endmodule

example/adder_tb.vcd
$date
	Fri Feb 24 22:40:02 2023
$end
$version
	Icarus Verilog
$end
$timescale
	1ns
$end
$scope module adder_test_g $end
$var wire 8 ! sum [7:0] $end
$var reg 8 " op1 [7:0] $end
$var reg 8 # op2 [7:0] $end
$scope module a1 $end
$var wire 8 $ operand0 [7:0] $end
$var wire 8 % operand1 [7:0] $end
$var reg 8 & result [7:0] $end
$upscope $end
$upscope $end
$enddefinitions $end
$comment Show the parameter values. $end
$dumpall
$end
#0
$dumpvars
b0 &
b0 %
b0 $
b0 #
b0 "
b0 !
$end
#200
b10100101 !
b10100101 &
b10000001 #
b10000001 %
b100100 "
b100100 $
#400
b1101100 !
b1101100 &
b1100011 #
b1100011 %
b1001 "
b1001 $
#600
b10011010 !
b10011010 &
b10001101 #
b10001101 %
b1101 "
b1101 $
#800
b1110111 !
b1110111 &
b10010 #
b10010 %
b1100101 "
b1100101 $
#1000
b1110 !
b1110 &
b1101 #
b1101 %
b1 "
b1 $
#1200
b10110011 !
b10110011 &
b111101 #
b111101 %
b1110110 "
b1110110 $
#1400
b1111001 !
b1111001 &
b10001100 #
b10001100 %
b11101101 "
b11101101 $
#1600
b10111111 !
b10111111 &
b11000110 #
b11000110 %
b11111001 "
b11111001 $
#1800
b1101111 !
b1101111 &
b10101010 #
b10101010 %
b11000101 "
b11000101 $
#2000
b1011100 !
b1011100 &
b1110111 #
b1110111 %
b11100101 "
b11100101 $
#2200
b10100001 !
b10100001 &
b10001111 #
b10001111 %
b10010 "
b10010 $
#2400
b11000000 !
b11000000 &
b11001110 #
b11001110 %
b11110010 "
b11110010 $
#2600
b10101101 !
b10101101 &
b11000101 #
b11000101 %
b11101000 "
b11101000 $
#2800
b11001 !
b11001 &
b10111101 #
b10111101 %
b1011100 "
b1011100 $
#3000
b10010010 !
b10010010 &
b1100101 #
b1100101 %
b101101 "
b101101 $
#3200
b1101101 !
b1101101 &
b1010 #
b1010 %
b1100011 "
b1100011 $
#3400
b10100000 !
b10100000 &
b100000 #
b100000 %
b10000000 "
b10000000 $
#3600
b1000111 !
b1000111 &
b10011101 #
b10011101 %
b10101010 "
b10101010 $
#3800
b10101001 !
b10101001 &
b10011 #
b10011 %
b10010110 "
b10010110 $
#4000
b1100000 !
b1100000 &
b1010011 #
b1010011 %
b1101 "
b1101 $
#4200
b1000000 !
b1000000 &
b11010101 #
b11010101 %
b1101011 "
b1101011 $
#4400
b10110000 !
b10110000 &
b10101110 #
b10101110 %
b10 "
b10 $
#4600
b11101100 !
b11101100 &
b11001111 #
b11001111 %
b11101 "
b11101 $
#4800
b101101 !
b101101 &
b1010 #
b1010 %
b100011 "
b100011 $
#5000
b110 !
b110 &
b111100 #
b111100 %
b11001010 "
b11001010 $
#5200
b1111100 !
b1111100 &
b10001010 #
b10001010 %
b11110010 "
b11110010 $
#5400
b11001 !
b11001 &
b11011000 #
b11011000 %
b1000001 "
b1000001 $
#5600
b1 !
b1 &
b10001001 #
b10001001 %
b1111000 "
b1111000 $
#5800
b10100001 !
b10100001 &
b10110110 #
b10110110 %
b11101011 "
b11101011 $
#6000
b1110100 !
b1110100 &
b10101110 #
b10101110 %
b11000110 "
b11000110 $
#6200
b11100110 !
b11100110 &
b101010 #
b101010 %
b10111100 "
b10111100 $
#6400
b1111100 !
b1111100 &
b1110001 #
b1110001 %
b1011 "
b1011 $
#6600
b11010100 !
b11010100 &
b1001111 #
b1001111 %
b10000101 "
b10000101 $
#6800
b1110101 !
b1110101 &
b111010 #
b111010 %
b111011 "
b111011 $
#7000
b10010011 !
b10010011 &
b10101 #
b10101 %
b1111110 "
b1111110 $
#7200
b11001010 !
b11001010 &
b11011001 #
b11011001 %
b11110001 "
b11110001 $
#7400
b10101110 !
b10101110 &
b1001100 #
b1001100 %
b1100010 "
b1100010 $
#7600
b101110 !
b101110 &
b10001111 #
b10001111 %
b10011111 "
b10011111 $
#7800
b10101111 !
b10101111 &
b10110111 #
b10110111 %
b11111000 "
b11111000 $
#8000
b11111011 !
b11111011 &
b1011100 #
b1011100 %
b10011111 "
b10011111 $
#8200
b11100100 !
b11100100 &
b10001001 #
b10001001 %
b1011011 "
b1011011 $
#8400
b11001 !
b11001 &
b11010000 #
b11010000 %
b1001001 "
b1001001 $
#8600
b101000 !
b101000 &
b1010001 #
b1010001 %
b11010111 "
b11010111 $
#8800
b10100010 !
b10100010 &
b1100 #
b1100 %
b10010110 "
b10010110 $
#9000
b10001010 !
b10001010 &
b11001000 #
b11001000 %
b11000010 "
b11000010 $
#9200
b10110100 !
b10110100 &
b111101 #
b111101 %
b1110111 "
b1110111 $
#9400
b10010000 !
b10010000 &
b1111110 #
b1111110 %
b10010 "
b10010 $
#9600
b10100110 !
b10100110 &
b111001 #
b111001 %
b1101101 "
b1101101 $
#9800
b11110010 !
b11110010 &
b11010011 #
b11010011 %
b11111 "
b11111 $
