simple_cpu/shifter.v
`timescale 10 ns / 1 ns

`define DATA_WIDTH 32

module shifter (
	input  [`DATA_WIDTH - 1:0] A,
	input  [              4:0] B,
	input  [              1:0] Shiftop,
	output [`DATA_WIDTH - 1:0] Result
);
	// TODO: Please add your logic code here
	wire signed[`DATA_WIDTH - 1:0] A;
	/* Shifter opcode */
	parameter LL = 2'b00, RL = 2'b10, RA = 2'b11;

	assign Result = (
		$signed({32{Shiftop == LL}}) & (A << B) |
		$signed({32{Shiftop == RL}}) & (A >> B) |
		$signed({32{Shiftop == RA}}) & (A >>> B)
	);
	/* The three $signed cannot be omitted!!! */
endmodule

shifter/shifter_tb.v
`timescale 10 ns / 1 ns
`define DATA_WIDTH 32
`define RND32 {$random} % (33'd1 << 32)
`define RND5 {$random} % (6'd1 << 5)

module shifter_test_g();
	reg  [`DATA_WIDTH - 1:0] A;
	reg  [              4:0] B;
	reg  [              1:0] Shiftop;
	wire [`DATA_WIDTH - 1:0] Result;

	shifter shifter_test_inst(A, B, Shiftop, Result);
	/* Shifter opcode */
	parameter LL = 2'b00, RL = 2'b10, RA = 2'b11;

	integer i;
	initial begin
		Shiftop = LL; // Left
		for (i = 0; i < 10; i = i + 1) begin
			A = `RND32;
			B = `RND5;
			#10;
		end

		Shiftop = RL; // Right Logic
		for (i = 0; i < 10; i = i + 1) begin
			A = `RND32;
			B = `RND5;
			#10;
		end

		Shiftop = RA; // Right Arthi
		for (i = 0; i < 10; i = i + 1) begin
			A = `RND32;
			B = `RND5;
			#10;
		end
		//$finish;
	end
	initial begin
		$dumpfile("shifter.vcd");
		$dumpvars(0, shifter_test_g);
	end
endmodule

shifter/shifter.vcd
$date
	Sat Apr 01 10:21:29 2023
$end
$version
	Icarus Verilog
$end
$timescale
	1ns
$end
$scope module shifter_test_g $end
$var wire 32 ! Result [31:0] $end
$var parameter 2 " LL $end
$var parameter 2 # RA $end
$var parameter 2 $ RL $end
$var reg 32 % A [31:0] $end
$var reg 5 & B [4:0] $end
$var reg 2 ' Shiftop [1:0] $end
$var integer 32 ( i [31:0] $end
$scope module shifter_test_inst $end
$var wire 32 ) A [31:0] $end
$var wire 5 * B [4:0] $end
$var wire 32 + Result [31:0] $end
$var wire 2 , Shiftop [1:0] $end
$var parameter 2 - LL $end
$var parameter 2 . RA $end
$var parameter 2 / RL $end
$upscope $end
$upscope $end
$enddefinitions $end
$comment Show the parameter values. $end
$dumpall
b10 /
b11 .
b0 -
b10 $
b11 #
b0 "
$end
#0
$dumpvars
b0 ,
b100100001010100110101001001000 +
b1 *
b10010000101010011010100100100 )
b0 (
b0 '
b1 &
b10010000101010011010100100100 %
b100100001010100110101001001000 !
$end
#100
b100100001001101011000001001000 !
b100100001001101011000001001000 +
b11 &
b11 *
b10000100100001001101011000001001 %
b10000100100001001101011000001001 )
b1 (
#200
b101111011000011010000000000000 !
b101111011000011010000000000000 +
b1101 &
b1101 *
b110101110010111101100001101 %
b110101110010111101100001101 )
b10 (
#300
b10001100101000000000000000000 !
b10001100101000000000000000000 +
b10010 &
b10010 *
b10110010110000101000010001100101 %
b10110010110000101000010001100101 )
b11 (
#400
b1111100011000000010000000000000 !
b1111100011000000010000000000000 +
b1101 &
b1101 *
b111100111110001100000001 %
b111100111110001100000001 )
b100 (
#500
b11000000000000000000000000000000 !
b11000000000000000000000000000000 +
b11101 &
b11101 *
b111011001000111111000101110110 %
b111011001000111111000101110110 )
b101 (
#600
b1000101011111101101000000000000 !
b1000101011111101101000000000000 +
b1100 &
b1100 *
b1110110110101000101011111101101 %
b1110110110101000101011111101101 )
b110 (
#700
b111111011110100111111001000000 !
b111111011110100111111001000000 +
b110 &
b110 *
b1111100111111011110100111111001 %
b1111100111111011110100111111001 )
b111 (
#800
b11011110000100110001010000000000 !
b11011110000100110001010000000000 +
b1010 &
b1010 *
b11100010111101111000010011000101 %
b11100010111101111000010011000101 )
b1000 (
#900
b11110010100000000000000000000000 !
b11110010100000000000000000000000 +
b10111 &
b10111 *
b1110010101011111111011111100101 %
b1110010101011111111011111100101 )
b1001 (
#1000
b10001001001100101 !
b10001001001100101 +
b1111 &
b1111 *
b10001001001100101101011000010010 %
b10001001001100101101011000010010 )
b10 '
b10 ,
b0 (
#1100
b11110010011000001 !
b11110010011000001 +
b1110 &
b1110 *
b1111001001100000110100111110010 %
b1111001001100000110100111110010 )
b1 (
#1200
b111101000000000001111010111 !
b111101000000000001111010111 +
b101 &
b101 *
b11110100000000000111101011101000 %
b11110100000000000111101011101000 )
b10 (
#1300
b1 !
b1 +
b11101 &
b11101 *
b101110010110000100100101011100 %
b101110010110000100100101011100 )
b11 (
#1400
b100101101010101101011000001 !
b100101101010101101011000001 +
b101 &
b101 *
b10010110101010110101100000101101 %
b10010110101010110101100000101101 )
b100 (
#1500
b1011000111101111011000 !
b1011000111101111011000 +
b1010 &
b1010 *
b10110001111011110110001001100011 %
b10110001111011110110001001100011 )
b101 (
#1600
b11000000001110110010001010000000 !
b11000000001110110010001010000000 +
b0 &
b0 *
b11000000001110110010001010000000 %
b11000000001110110010001010000000 )
b110 (
#1700
b10 !
b10 +
b11101 &
b11101 *
b1010101011110000100010110101010 %
b1010101011110000100010110101010 )
b111 (
#1800
b1100101100100 !
b1100101100100 +
b10011 &
b10011 *
b11001011001000000011111010010110 %
b11001011001000000011111010010110 )
b1000 (
#1900
b1000011010111 !
b1000011010111 +
b10000110101111000011100000001101 %
b10000110101111000011100000001101 )
b1001 (
#2000
b110101100 !
b110101100 +
b10101 &
b10101 *
b110101100111111101110101101011 %
b110101100111111101110101101011 )
b11 '
b11 ,
b0 (
#2100
b11111111111111100000010001011101 !
b11111111111111100000010001011101 +
b1110 &
b1110 *
b10000001000101110100101000000010 %
b10000001000101110100101000000010 )
b1 (
#2200
b1110111111111 !
b1110111111111 +
b1111 &
b1111 *
b1110111111111110100100011101 %
b1110111111111110100100011101 )
b10 (
#2300
b1000110000100010010 !
b1000110000100010010 +
b1010 &
b1010 *
b10001100001000100100100100011 %
b10001100001000100100100100011 )
b11 (
#2400
b11111111111111111111111111111110 !
b11111111111111111111111111111110 +
b11100 &
b11100 *
b11100101011100110000101011001010 %
b11100101011100110000101011001010 )
b100 (
#2500
b111100101101000101111 !
b111100101101000101111 +
b1010 &
b1010 *
b1111001011010001011110111110010 %
b1111001011010001011110111110010 )
b101 (
#2600
b100000 !
b100000 +
b11000 &
b11000 *
b100000110001001011001101000001 %
b100000110001001011001101000001 )
b110 (
#2700
b111100001000001111001 !
b111100001000001111001 +
b1001 &
b1001 *
b111100001000001111001101111000 %
b111100001000001111001101111000 )
b111 (
#2800
b111010111 !
b111010111 +
b10110 &
b10110 *
b1110101110001010000110111101011 %
b1110101110001010000110111101011 )
b1000 (
#2900
b11000110100101111 !
b11000110100101111 +
b1110 &
b1110 *
b1100011010010111111100111000110 %
b1100011010010111111100111000110 )
b1001 (
#3000
b1010 (
