custom_cpu/riscv32/mult/mult_booth.v
/* Data with, not including signal bit */
`define DATA_WIDTH 31

module multiplier(
    input [`DATA_WIDTH:0] A,
    input [`DATA_WIDTH:0] B,
    output [2 * `DATA_WIDTH + 1:0] P,
    input clk,
    input rst,
    output done
);

    localparam s_ADD = 3'b001,
        s_SFT = 3'b010,
        s_DNE = 3'b100;

    /* counter C */
    localparam DW = 5'd31,   /* `DATA_WIDTH */
        ZEROy = 5'd0,
        ZEROd = 33'd0;
    reg [4:0] ymr;

    reg [`DATA_WIDTH + 1:0] ACC, AX, Q;
    /*  ACC:    accumulator;
        AX:      multiplier A;
        Q:      multiplier B and result. */

    reg [2:0] current_state, next_state;

    /* FSM: current state */
    always @ (posedge clk) begin
        if (rst)
            if (B[0] == 1'b0)
                current_state <= s_SFT;
            else
                current_state <= s_ADD;
        else
            current_state <= next_state;
    end

    /* FSM: next state */
    always @ (*) begin
        case (current_state)
        s_ADD:
            if (ymr == ZEROy)
                next_state = s_DNE;
            else
                next_state = s_SFT;
        s_SFT:
            if (ymr == ZEROy)
                next_state = s_DNE;
            else if (Q[2] == Q[1])
                next_state = s_SFT;
            else    /* do + or - */
                next_state = s_ADD;
        default:    /* s_DNE */
            next_state = s_DNE;
        endcase
    end

    /* FSM: output */
    /* ymr */
    always @ (posedge clk) begin
        if (rst)
            ymr <= DW;
        else if (current_state == s_SFT) // && ymr == ZEROy
            ymr <= ymr - 1;
    end
    /* AX */
    always @ (posedge clk) begin
        if (rst)
            /* two signal bits */
            AX <= { A[`DATA_WIDTH],A };
    end
    /* ACC */
    always @ (posedge clk) begin
        if (rst)
            ACC <= ZEROd;
        else if (current_state == s_ADD)
            ACC <= ACC + (Q[1] ? ~AX : AX) + Q[1];
        else if (current_state == s_SFT && ymr != ZEROy)
            ACC <= { ACC[`DATA_WIDTH + 1],ACC[`DATA_WIDTH + 1:1] };
    end
    /* Q */
    always @ (posedge clk) begin
        if (rst)
            Q <= { B,1'd0 };
        else if (current_state == s_SFT && ymr != ZEROy)
            Q <= { ACC[0],Q[`DATA_WIDTH + 1:1] };
    end
    /* other */
    assign done = !rst && (current_state == s_DNE);
    assign P = { ACC,Q[`DATA_WIDTH + 1:2] };

endmodule

custom_cpu/riscv32/mult/mult_booth_tb.v
`timescale 10 ns / 1 ns

`define RND32 {$random} % (33'd1 << 32)
`define DATA_WIDTH 31

module multiplier_test_g();
	reg [`DATA_WIDTH:0] A;
	reg [`DATA_WIDTH:0] B;
	wire [2 * `DATA_WIDTH + 1:0] P;
	reg clk;
	reg rst;
	wire done;

	integer i, j;

	multiplier multiplier_test_inst(A, B, P, clk, rst, done);

	initial begin
		for (i = 0; i < 20; i = i + 1) begin
			clk = 0;
			rst = 1;
			A = `RND32;
			B = `RND32;
			#10 clk = 1;
			#10 rst = 0;
			for (j = 0; j < 64; j = j + 1) begin
				clk = 0;
				#10 clk = 1;
				#10;
			end
		end
	end

	initial begin
		$dumpfile("multiplier.vcd");
		$dumpvars(0, multiplier_test_g);
	end
endmodule

custom_cpu/riscv32/mult/multiplier.vcd
$date
	Thu May 25 08:38:35 2023
$end
$version
	Icarus Verilog
$end
$timescale
	1ns
$end
$scope module multiplier_test_g $end
$var wire 1 ! done $end
$var wire 64 " P [63:0] $end
$var reg 32 # A [31:0] $end
$var reg 32 $ B [31:0] $end
$var reg 1 % clk $end
$var reg 1 & rst $end
$var integer 32 ' i [31:0] $end
$var integer 32 ( j [31:0] $end
$scope module multiplier_test_inst $end
$var wire 32 ) A [31:0] $end
$var wire 32 * B [31:0] $end
$var wire 1 % clk $end
$var wire 1 ! done $end
$var wire 1 & rst $end
$var wire 64 + P [63:0] $end
$var parameter 5 , DW $end
$var parameter 33 - ZEROd $end
$var parameter 5 . ZEROy $end
$var parameter 3 / s_ADD $end
$var parameter 3 0 s_DNE $end
$var parameter 3 1 s_SFT $end
$var reg 33 2 ACC [32:0] $end
$var reg 33 3 AX [32:0] $end
$var reg 33 4 Q [32:0] $end
$var reg 3 5 current_state [2:0] $end
$var reg 3 6 next_state [2:0] $end
$var reg 5 7 ymr [4:0] $end
$upscope $end
$upscope $end
$enddefinitions $end
$comment Show the parameter values. $end
$dumpall
b10 1
b100 0
b1 /
b0 .
b0 -
b11111 ,
$end
#0
$dumpvars
bx 7
bx 6
bx 5
bx 4
bx 3
bx 2
bx +
b11000000100010010101111010000001 *
b10010000101010011010100100100 )
bx (
b0 '
1&
0%
b11000000100010010101111010000001 $
b10010000101010011010100100100 #
bx "
0!
$end
#100
b10 6
b1 5
b11111 7
b10010000101010011010100100100 3
b1100000010001001010111101000000 "
b1100000010001001010111101000000 +
b0 2
b110000001000100101011110100000010 4
1%
#200
0%
b0 (
0&
#300
b1 6
b1111011011110101011001010110111001100000010001001010111101000000 "
b1111011011110101011001010110111001100000010001001010111101000000 +
b111101101111010101100101011011100 2
b10 5
1%
#400
0%
b1 (
#500
b10 6
b1 5
b11110 7
b1111101101111010101100101011011100110000001000100101011110100000 "
b1111101101111010101100101011011100110000001000100101011110100000 +
b111110110111101010110010101101110 2
b11000000100010010101111010000001 4
1%
#600
0%
b10 (
#700
b10010000101010011010100100100110000001000100101011110100000 "
b10010000101010011010100100100110000001000100101011110100000 +
b1001000010101001101010010010 2
b10 5
1%
#800
0%
b11 (
#900
b11101 7
b1001000010101001101010010010011000000100010010101111010000 "
b1001000010101001101010010010011000000100010010101111010000 +
b100100001010100110101001001 2
b1100000010001001010111101000000 4
1%
#1000
0%
b100 (
#1100
b100110000001000100101011110100000 4
b100100001010100110101001001001100000010001001010111101000 "
b100100001010100110101001001001100000010001001010111101000 +
b10010000101010011010100100 2
b11100 7
1%
#1200
0%
b101 (
#1300
b11011 7
b10010000101010011010100100100110000001000100101011110100 "
b10010000101010011010100100100110000001000100101011110100 +
b1001000010101001101010010 2
b10011000000100010010101111010000 4
1%
#1400
0%
b110 (
#1500
b1001100000010001001010111101000 4
b1001000010101001101010010010011000000100010010101111010 "
b1001000010101001101010010010011000000100010010101111010 +
b100100001010100110101001 2
b11010 7
1%
#1600
0%
b111 (
#1700
b1 6
b11001 7
b100100001010100110101001001001100000010001001010111101 "
b100100001010100110101001001001100000010001001010111101 +
b10010000101010011010100 2
b100100110000001000100101011110100 4
1%
#1800
0%
b1000 (
#1900
b10 6
b10010011000000100010010101111010 4
b10010000101010011010100100100110000001000100101011110 "
b10010000101010011010100100100110000001000100101011110 +
b1001000010101001101010 2
b11000 7
b1 5
1%
#2000
0%
b1001 (
#2100
b1 6
b10 5
b1111011100000111011110101010001100100100110000001000100101011110 "
b1111011100000111011110101010001100100100110000001000100101011110 +
b111101110000011101111010101000110 2
1%
#2200
0%
b1010 (
#2300
b10 6
b1001001100000010001001010111101 4
b1111101110000011101111010101000110010010011000000100010010101111 "
b1111101110000011101111010101000110010010011000000100010010101111 +
b111110111000001110111101010100011 2
b10111 7
b1 5
1%
#2400
0%
b1011 (
#2500
b1 6
b10 5
b10010001110010101111110001110010010011000000100010010101111 "
b10010001110010101111110001110010010011000000100010010101111 +
b1001000111001010111111000111 2
1%
#2600
0%
b1100 (
#2700
b10 6
b100100100110000001000100101011110 4
b1001000111001010111111000111001001001100000010001001010111 "
b1001000111001010111111000111001001001100000010001001010111 +
b100100011100101011111100011 2
b10110 7
b1 5
1%
#2800
0%
b1101 (
#2900
b10 5
b1111100100111100100100010101111111001001001100000010001001010111 "
b1111100100111100100100010101111111001001001100000010001001010111 +
b111110010011110010010001010111111 2
1%
#3000
0%
b1110 (
#3100
b110010010011000000100010010101111 4
b1111110010011110010010001010111111100100100110000001000100101011 "
b1111110010011110010010001010111111100100100110000001000100101011 +
b111111001001111001001000101011111 2
b10101 7
1%
#3200
0%
b1111 (
#3300
b10100 7
b1111111001001111001001000101011111110010010011000000100010010101 "
b1111111001001111001001000101011111110010010011000000100010010101 +
b111111100100111100100100010101111 2
b111001001001100000010001001010111 4
1%
#3400
0%
b10000 (
#3500
b1 6
b111100100100110000001000100101011 4
b1111111100100111100100100010101111111001001001100000010001001010 "
b1111111100100111100100100010101111111001001001100000010001001010 +
b111111110010011110010010001010111 2
b10011 7
1%
#3600
0%
b10001 (
#3700
b10 6
b1 5
b10010 7
b1111111110010011110010010001010111111100100100110000001000100101 "
b1111111110010011110010010001010111111100100100110000001000100101 +
b111111111001001111001001000101011 2
b111110010010011000000100010010101 4
1%
#3800
0%
b10010 (
#3900
b1 6
b100010011110011000111010011111111100100100110000001000100101 "
b100010011110011000111010011111111100100100110000001000100101 +
b10001001111001100011101001111 2
b10 5
1%
#4000
0%
b10011 (
#4100
b10 6
b1 5
b10001 7
b10001001111001100011101001111111110010010011000000100010010 "
b10001001111001100011101001111111110010010011000000100010010 +
b1000100111100110001110100111 2
b111111001001001100000010001001010 4
1%
#4200
0%
b10100 (
#4300
b1 6
b1111101101000100100101110100000111111110010010011000000100010010 "
b1111101101000100100101110100000111111110010010011000000100010010 +
b111110110100010010010111010000011 2
b10 5
1%
#4400
0%
b10101 (
#4500
b10 6
b1 5
b10000 7
b1111110110100010010010111010000011111111001001001100000010001001 "
b1111110110100010010010111010000011111111001001001100000010001001 +
b111111011010001001001011101000001 2
b111111100100100110000001000100101 4
1%
#4600
0%
b10110 (
#4700
b1 6
b11010101100111001100011001011111111001001001100000010001001 "
b11010101100111001100011001011111111001001001100000010001001 +
b1101010110011100110001100101 2
b10 5
1%
#4800
0%
b10111 (
#4900
b10 6
b1 5
b1111 7
b1101010110011100110001100101111111100100100110000001000100 "
b1101010110011100110001100101111111100100100110000001000100 +
b110101011001110011000110010 2
b111111110010010011000000100010010 4
1%
#5000
0%
b11000 (
#5100
b1 6
b1111101001001011110110001000011101111111100100100110000001000100 "
b1111101001001011110110001000011101111111100100100110000001000100 +
b111110100100101111011000100001110 2
b10 5
1%
#5200
0%
b11001 (
#5300
b10 6
b1 5
b1110 7
b1111110100100101111011000100001110111111110010010011000000100010 "
b1111110100100101111011000100001110111111110010010011000000100010 +
b111111010010010111101100010000111 2
b11111111001001001100000010001001 4
1%
#5400
0%
b11010 (
#5500
b11000110000100001101101010110111111110010010011000000100010 "
b11000110000100001101101010110111111110010010011000000100010 +
b1100011000010000110110101011 2
b10 5
1%
#5600
0%
b11011 (
#5700
b1 6
b1101 7
b1100011000010000110110101011011111111001001001100000010001 "
b1100011000010000110110101011011111111001001001100000010001 +
b110001100001000011011010101 2
b101111111100100100110000001000100 4
1%
#5800
0%
b11100 (
#5900
b10 6
b110111111110010010011000000100010 4
b110001100001000011011010101101111111100100100110000001000 "
b110001100001000011011010101101111111100100100110000001000 +
b11000110000100001101101010 2
b1100 7
b1 5
1%
#6000
0%
b11101 (
#6100
b1 6
b10 5
b1111100010000001100001110010001101101111111100100100110000001000 "
b1111100010000001100001110010001101101111111100100100110000001000 +
b111110001000000110000111001000110 2
1%
#6200
0%
b11110 (
#6300
b10 6
b11011111111001001001100000010001 4
b1111110001000000110000111001000110110111111110010010011000000100 "
b1111110001000000110000111001000110110111111110010010011000000100 +
b111111000100000011000011100100011 2
b1011 7
b1 5
1%
#6400
0%
b11111 (
#6500
b10 5
b10101001011010111100010001110110111111110010010011000000100 "
b10101001011010111100010001110110111111110010010011000000100 +
b1010100101101011110001000111 2
1%
#6600
0%
b100000 (
#6700
b101101111111100100100110000001000 4
b1010100101101011110001000111011011111111001001001100000010 "
b1010100101101011110001000111011011111111001001001100000010 +
b101010010110101111000100011 2
b1010 7
1%
#6800
0%
b100001 (
#6900
b1 6
b1001 7
b101010010110101111000100011101101111111100100100110000001 "
b101010010110101111000100011101101111111100100100110000001 +
b10101001011010111100010001 2
b110110111111110010010011000000100 4
1%
#7000
0%
b100010 (
#7100
b10 6
b111011011111111001001001100000010 4
b10101001011010111100010001110110111111110010010011000000 "
b10101001011010111100010001110110111111110010010011000000 +
b1010100101101011110001000 2
b1000 7
b1 5
1%
#7200
0%
b100011 (
#7300
b1 6
b10 5
b1111011110011110110100010011001001110110111111110010010011000000 "
b1111011110011110110100010011001001110110111111110010010011000000 +
b111101111001111011010001001100100 2
1%
#7400
0%
b100100 (
#7500
b10 6
b11101101111111100100100110000001 4
b1111101111001111011010001001100100111011011111111001001001100000 "
b1111101111001111011010001001100100111011011111111001001001100000 +
b111110111100111101101000100110010 2
b111 7
b1 5
1%
#7600
0%
b100101 (
#7700
b10 5
b10011011010000000110010101100111011011111111001001001100000 "
b10011011010000000110010101100111011011111111001001001100000 +
b1001101101000000011001010110 2
1%
#7800
0%
b100110 (
#7900
b1110110111111110010010011000000 4
b1001101101000000011001010110011101101111111100100100110000 "
b1001101101000000011001010110011101101111111100100100110000 +
b100110110100000001100101011 2
b110 7
1%
#8000
0%
b100111 (
#8100
b101 7
b100110110100000001100101011001110110111111110010010011000 "
b100110110100000001100101011001110110111111110010010011000 +
b10011011010000000110010101 2
b100111011011111111001001001100000 4
1%
#8200
0%
b101000 (
#8300
b110011101101111111100100100110000 4
b10011011010000000110010101100111011011111111001001001100 "
b10011011010000000110010101100111011011111111001001001100 +
b1001101101000000011001010 2
b100 7
1%
#8400
0%
b101001 (
#8500
b11 7
b1001101101000000011001010110011101101111111100100100110 "
b1001101101000000011001010110011101101111111100100100110 +
b100110110100000001100101 2
b11001110110111111110010010011000 4
1%
#8600
0%
b101010 (
#8700
b1 6
b101100111011011111111001001001100 4
b100110110100000001100101011001110110111111110010010011 "
b100110110100000001100101011001110110111111110010010011 +
b10011011010000000110010 2
b10 7
1%
#8800
0%
b101011 (
#8900
b10 6
b1 5
b1 7
b10011011010000000110010101100111011011111111001001001 "
b10011011010000000110010101100111011011111111001001001 +
b1001101101000000011001 2
b10110011101101111111100100100110 4
1%
#9000
0%
b101100 (
#9100
b1111011100001000110011010111101010101100111011011111111001001001 "
b1111011100001000110011010111101010101100111011011111111001001001 +
b111101110000100011001101011110101 2
b10 5
1%
#9200
0%
b101101 (
#9300
b100 6
b0 7
b1111101110000100011001101011110101010110011101101111111100100100 "
b1111101110000100011001101011110101010110011101101111111100100100 +
b111110111000010001100110101111010 2
b101011001110110111111110010010011 4
1%
#9400
0%
b101110 (
#9500
1!
b11111 7
b100 5
1%
#9600
0%
b101111 (
#9700
1%
#9800
0%
b110000 (
#9900
1%
#10000
0%
b110001 (
#10100
1%
#10200
0%
b110010 (
#10300
1%
#10400
0%
b110011 (
#10500
1%
#10600
0%
b110100 (
#10700
1%
#10800
0%
b110101 (
#10900
1%
#11000
0%
b110110 (
#11100
1%
#11200
0%
b110111 (
#11300
1%
#11400
0%
b111000 (
#11500
1%
#11600
0%
b111001 (
#11700
1%
#11800
0%
b111010 (
#11900
1%
#12000
0%
b111011 (
#12100
1%
#12200
0%
b111100 (
#12300
1%
#12400
0%
b111101 (
#12500
1%
#12600
0%
b111110 (
#12700
1%
#12800
0%
b111111 (
#12900
1%
#13000
0!
b10110001111100000101011001100011 $
b10110001111100000101011001100011 *
b10000100100001001101011000001001 #
b10000100100001001101011000001001 )
1&
0%
b1 '
b1000000 (
#13100
b10 6
b101100011111000001010110011000110 4
b1011000111110000010101100110001 "
b1011000111110000010101100110001 +
b0 2
b110000100100001001101011000001001 3
b1 5
1%
#13200
0%
b0 (
0&
#13300
b10 5
b11110110111101100101001111101111011000111110000010101100110001 "
b11110110111101100101001111101111011000111110000010101100110001 +
b1111011011110110010100111110111 2
1%
#13400
0%
b1 (
#13500
b1 6
b110110001111100000101011001100011 4
b1111011011110110010100111110111101100011111000001010110011000 "
b1111011011110110010100111110111101100011111000001010110011000 +
b111101101111011001010011111011 2
b11110 7
1%
#13600
0%
b10 (
#13700
b10 6
b1 5
b11101 7
b111101101111011001010011111011110110001111100000101011001100 "
b111101101111011001010011111011110110001111100000101011001100 +
b11110110111101100101001111101 2
b111011000111110000010101100110001 4
1%
#13800
0%
b11 (
#13900
b1101000110110001110100000100001101110110001111100000101011001100 "
b1101000110110001110100000100001101110110001111100000101011001100 +
b110100011011000111010000010000110 2
b10 5
1%
#14000
0%
b100 (
#14100
b11100 7
b1110100011011000111010000010000110111011000111110000010101100110 "
b1110100011011000111010000010000110111011000111110000010101100110 +
b111010001101100011101000001000011 2
b11101100011111000001010110011000 4
1%
#14200
0%
b101 (
#14300
b1 6
b101110110001111100000101011001100 4
b1111010001101100011101000001000011011101100011111000001010110011 "
b1111010001101100011101000001000011011101100011111000001010110011 +
b111101000110110001110100000100001 2
b11011 7
1%
#14400
0%
b110 (
#14500
b10 6
b1 5
b11010 7
b1111101000110110001110100000100001101110110001111100000101011001 "
b1111101000110110001110100000100001101110110001111100000101011001 +
b111110100011011000111010000010000 2
b110111011000111110000010101100110 4
1%
#14600
0%
b111 (
#14700
b11011111110011110011110000001111101110110001111100000101011001 "
b11011111110011110011110000001111101110110001111100000101011001 +
b1101111111001111001111000000111 2
b10 5
1%
#14800
0%
b1000 (
#14900
b1 6
b11001 7
b1101111111001111001111000000111110111011000111110000010101100 "
b1101111111001111001111000000111110111011000111110000010101100 +
b110111111100111100111100000011 2
b111011101100011111000001010110011 4
1%
#15000
0%
b1001 (
#15100
b10 6
b111101110110001111100000101011001 4
b110111111100111100111100000011111011101100011111000001010110 "
b110111111100111100111100000011111011101100011111000001010110 +
b11011111110011110011110000001 2
b11000 7
b1 5
1%
#15200
0%
b1010 (
#15300
b10 5
b1101000000111111010111101100010101111011101100011111000001010110 "
b1101000000111111010111101100010101111011101100011111000001010110 +
b110100000011111101011110110001010 2
1%
#15400
0%
b1011 (
#15500
b1 6
b11110111011000111110000010101100 4
b1110100000011111101011110110001010111101110110001111100000101011 "
b1110100000011111101011110110001010111101110110001111100000101011 +
b111010000001111110101111011000101 2
b10111 7
1%
#15600
0%
b1100 (
#15700
b10 6
b1 5
b10110 7
b1111010000001111110101111011000101011110111011000111110000010101 "
b1111010000001111110101111011000101011110111011000111110000010101 +
b111101000000111111010111101100010 2
b101111011101100011111000001010110 4
1%
#15800
0%
b1101 (
#15900
b11000111001101011011001010110011011110111011000111110000010101 "
b11000111001101011011001010110011011110111011000111110000010101 +
b1100011100110101101100101011001 2
b10 5
1%
#16000
0%
b1110 (
#16100
b1 6
b10101 7
b1100011100110101101100101011001101111011101100011111000001010 "
b1100011100110101101100101011001101111011101100011111000001010 +
b110001110011010110110010101100 2
b110111101110110001111100000101011 4
1%
#16200
0%
b1111 (
#16300
b10 6
b11011110111011000111110000010101 4
b110001110011010110110010101100110111101110110001111100000101 "
b110001110011010110110010101100110111101110110001111100000101 +
b11000111001101011011001010110 2
b10100 7
b1 5
1%
#16400
0%
b10000 (
#16500
b1 6
b10 5
b1100111010110101110001100010111110110111101110110001111100000101 "
b1100111010110101110001100010111110110111101110110001111100000101 +
b110011101011010111000110001011111 2
1%
#16600
0%
b10001 (
#16700
b10 6
b101101111011101100011111000001010 4
b1110011101011010111000110001011111011011110111011000111110000010 "
b1110011101011010111000110001011111011011110111011000111110000010 +
b111001110101101011100011000101111 2
b10011 7
b1 5
1%
#16800
0%
b10010 (
#16900
b1 6
b10 5
b10010100011000011110000001001101011011110111011000111110000010 "
b10010100011000011110000001001101011011110111011000111110000010 +
b1001010001100001111000000100110 2
1%
#17000
0%
b10011 (
#17100
b10 6
b10110111101110110001111100000101 4
b1001010001100001111000000100110101101111011101100011111000001 "
b1001010001100001111000000100110101101111011101100011111000001 +
b100101000110000111100000010011 2
b10010 7
b1 5
1%
#17200
0%
b10100 (
#17300
b1 6
b10 5
b1101010011001110101001110000111000101101111011101100011111000001 "
b1101010011001110101001110000111000101101111011101100011111000001 +
b110101001100111010100111000011100 2
1%
#17400
0%
b10101 (
#17500
b10 6
b1011011110111011000111110000010 4
b1110101001100111010100111000011100010110111101110110001111100000 "
b1110101001100111010100111000011100010110111101110110001111100000 +
b111010100110011101010011100001110 2
b10001 7
b1 5
1%
#17600
0%
b10110 (
#17700
b1 6
b10 5
b10100000100100111010001000001010010110111101110110001111100000 "
b10100000100100111010001000001010010110111101110110001111100000 +
b1010000010010011101000100000101 2
1%
#17800
0%
b10111 (
#17900
b10 6
b100101101111011101100011111000001 4
b1010000010010011101000100000101001011011110111011000111110000 "
b1010000010010011101000100000101001011011110111011000111110000 +
b101000001001001110100010000010 2
b10000 7
b1 5
1%
#18000
0%
b11000 (
#18100
b10 5
b1101011001010100110111110100010111001011011110111011000111110000 "
b1101011001010100110111110100010111001011011110111011000111110000 +
b110101100101010011011111010001011 2
1%
#18200
0%
b11001 (
#18300
b110010110111101110110001111100000 4
b1110101100101010011011111010001011100101101111011101100011111000 "
b1110101100101010011011111010001011100101101111011101100011111000 +
b111010110010101001101111101000101 2
b1111 7
1%
#18400
0%
b11010 (
#18500
b1110 7
b1111010110010101001101111101000101110010110111101110110001111100 "
b1111010110010101001101111101000101110010110111101110110001111100 +
b111101011001010100110111110100010 2
b111001011011110111011000111110000 4
1%
#18600
0%
b11011 (
#18700
b11100101101111011101100011111000 4
b1111101011001010100110111110100010111001011011110111011000111110 "
b1111101011001010100110111110100010111001011011110111011000111110 +
b111110101100101010011011111010001 2
b1101 7
1%
#18800
0%
b11100 (
#18900
b1 6
b1100 7
b1111110101100101010011011111010001011100101101111011101100011111 "
b1111110101100101010011011111010001011100101101111011101100011111 +
b111111010110010101001101111101000 2
b101110010110111101110110001111100 4
1%
#19000
0%
b11101 (
#19100
b10 6
b10111001011011110111011000111110 4
b1111111010110010101001101111101000101110010110111101110110001111 "
b1111111010110010101001101111101000101110010110111101110110001111 +
b111111101011001010100110111110100 2
b1011 7
b1 5
1%
#19200
0%
b11110 (
#19300
b10 5
b11110001110000001110111111010110101110010110111101110110001111 "
b11110001110000001110111111010110101110010110111101110110001111 +
b1111000111000000111011111101011 2
1%
#19400
0%
b11111 (
#19500
b101011100101101111011101100011111 4
b1111000111000000111011111101011010111001011011110111011000111 "
b1111000111000000111011111101011010111001011011110111011000111 +
b111100011100000011101111110101 2
b1010 7
1%
#19600
0%
b100000 (
#19700
b1001 7
b111100011100000011101111110101101011100101101111011101100011 "
b111100011100000011101111110101101011100101101111011101100011 +
b11110001110000001110111111010 2
b110101110010110111101110110001111 4
1%
#19800
0%
b100001 (
#19900
b11010111001011011110111011000111 4
b11110001110000001110111111010110101110010110111101110110001 "
b11110001110000001110111111010110101110010110111101110110001 +
b1111000111000000111011111101 2
b1000 7
1%
#20000
0%
b100010 (
#20100
b1 6
b111 7
b1111000111000000111011111101011010111001011011110111011000 "
b1111000111000000111011111101011010111001011011110111011000 +
b111100011100000011101111110 2
b101101011100101101111011101100011 4
1%
#20200
0%
b100011 (
#20300
b10 6
b10110101110010110111101110110001 4
b111100011100000011101111110101101011100101101111011101100 "
b111100011100000011101111110101101011100101101111011101100 +
b11110001110000001110111111 2
b110 7
b1 5
1%
#20400
0%
b100100 (
#20500
b10 5
b1100010000100101111011001110010000101101011100101101111011101100 "
b1100010000100101111011001110010000101101011100101101111011101100 +
b110001000010010111101100111001000 2
1%
#20600
0%
b100101 (
#20700
b1011010111001011011110111011000 4
b1110001000010010111101100111001000010110101110010110111101110110 "
b1110001000010010111101100111001000010110101110010110111101110110 +
b111000100001001011110110011100100 2
b101 7
1%
#20800
0%
b100110 (
#20900
b1 6
b100 7
b1111000100001001011110110011100100001011010111001011011110111011 "
b1111000100001001011110110011100100001011010111001011011110111011 +
b111100010000100101111011001110010 2
b101101011100101101111011101100 4
1%
#21000
0%
b100111 (
#21100
b10 6
b10110101110010110111101110110 4
b1111100010000100101111011001110010000101101011100101101111011101 "
b1111100010000100101111011001110010000101101011100101101111011101 +
b111110001000010010111101100111001 2
b11 7
b1 5
1%
#21200
0%
b101000 (
#21300
b10 5
b11011001000010010100101001100000000101101011100101101111011101 "
b11011001000010010100101001100000000101101011100101101111011101 +
b1101100100001001010010100110000 2
1%
#21400
0%
b101001 (
#21500
b1 6
b1011010111001011011110111011 4
b1101100100001001010010100110000000010110101110010110111101110 "
b1101100100001001010010100110000000010110101110010110111101110 +
b110110010000100101001010011000 2
b10 7
1%
#21600
0%
b101010 (
#21700
b10 6
b1 5
b1 7
b110110010000100101001010011000000001011010111001011011110111 "
b110110010000100101001010011000000001011010111001011011110111 +
b11011001000010010100101001100 2
b101101011100101101111011101 4
1%
#21800
0%
b101011 (
#21900
b1 6
b1100111111010010111111111010101010000001011010111001011011110111 "
b1100111111010010111111111010101010000001011010111001011011110111 +
b110011111101001011111111101010101 2
b10 5
1%
#22000
0%
b101100 (
#22100
b100 6
b1 5
b0 7
b1110011111101001011111111101010101000000101101011100101101111011 "
b1110011111101001011111111101010101000000101101011100101101111011 +
b111001111110100101111111110101010 2
b100000010110101110010110111101110 4
1%
#22200
0%
b101101 (
#22300
1!
b10010110100111000101001101000011000000101101011100101101111011 "
b10010110100111000101001101000011000000101101011100101101111011 +
b1001011010011100010100110100001 2
b100 5
1%
#22400
0%
b101110 (
#22500
1%
#22600
0%
b101111 (
#22700
1%
#22800
0%
b110000 (
#22900
1%
#23000
0%
b110001 (
#23100
1%
#23200
0%
b110010 (
#23300
1%
#23400
0%
b110011 (
#23500
1%
#23600
0%
b110100 (
#23700
1%
#23800
0%
b110101 (
#23900
1%
#24000
0%
b110110 (
#24100
1%
#24200
0%
b110111 (
#24300
1%
#24400
0%
b111000 (
#24500
1%
#24600
0%
b111001 (
#24700
1%
#24800
0%
b111010 (
#24900
1%
#25000
0%
b111011 (
#25100
1%
#25200
0%
b111100 (
#25300
1%
#25400
0%
b111101 (
#25500
1%
#25600
0%
b111110 (
#25700
1%
#25800
0%
b111111 (
#25900
1%
#26000
0!
b1000110110111111001100110001101 $
b1000110110111111001100110001101 *
b110101110010111101100001101 #
b110101110010111101100001101 )
1&
0%
b10 '
b1000000 (
#26100
b10 6
b1 5
b11111 7
b110101110010111101100001101 3
b100011011011111100110011000110 "
b100011011011111100110011000110 +
b0 2
b10001101101111110011001100011010 4
1%
#26200
0%
b0 (
0&
#26300
b1 6
b1111110010100011010000100111100110100011011011111100110011000110 "
b1111110010100011010000100111100110100011011011111100110011000110 +
b111111001010001101000010011110011 2
b10 5
1%
#26400
0%
b1 (
#26500
b10 6
b1 5
b11110 7
b1111111001010001101000010011110011010001101101111110011001100011 "
b1111111001010001101000010011110011010001101101111110011001100011 +
b111111100101000110100001001111001 2
b101000110110111111001100110001101 4
1%
#26600
0%
b10 (
#26700
b1 6
b110101110010111101100001101010001101101111110011001100011 "
b110101110010111101100001101010001101101111110011001100011 +
b11010111001011110110000110 2
b10 5
1%
#26800
0%
b11 (
#26900
b10 6
b1 5
b11101 7
b11010111001011110110000110101000110110111111001100110001 "
b11010111001011110110000110101000110110111111001100110001 +
b1101011100101111011000011 2
b10100011011011111100110011000110 4
1%
#27000
0%
b100 (
#27100
b1111110101111010011100011101101100101000110110111111001100110001 "
b1111110101111010011100011101101100101000110110111111001100110001 +
b111111010111101001110001110110110 2
b10 5
1%
#27200
0%
b101 (
#27300
b1 6
b11100 7
b1111111010111101001110001110110110010100011011011111100110011000 "
b1111111010111101001110001110110110010100011011011111100110011000 +
b111111101011110100111000111011011 2
b1010001101101111110011001100011 4
1%
#27400
0%
b110 (
#27500
b10 6
b100101000110110111111001100110001 4
b1111111101011110100111000111011011001010001101101111110011001100 "
b1111111101011110100111000111011011001010001101101111110011001100 +
b111111110101111010011100011101101 2
b11011 7
b1 5
1%
#27600
0%
b111 (
#27700
b10 5
b1010111011010110011111110101001010001101101111110011001100 "
b1010111011010110011111110101001010001101101111110011001100 +
b101011101101011001111111010 2
1%
#27800
0%
b1000 (
#27900
b10010100011011011111100110011000 4
b101011101101011001111111010100101000110110111111001100110 "
b101011101101011001111111010100101000110110111111001100110 +
b10101110110101100111111101 2
b11010 7
1%
#28000
0%
b1001 (
#28100
b1 6
b11001 7
b10101110110101100111111101010010100011011011111100110011 "
b10101110110101100111111101010010100011011011111100110011 +
b1010111011010110011111110 2
b101001010001101101111110011001100 4
1%
#28200
0%
b1010 (
#28300
b10 6
b10100101000110110111111001100110 4
b1010111011010110011111110101001010001101101111110011001 "
b1010111011010110011111110101001010001101101111110011001 +
b101011101101011001111111 2
b11000 7
b1 5
1%
#28400
0%
b1011 (
#28500
b10 5
b1111110011111010101011011011100100101001010001101101111110011001 "
b1111110011111010101011011011100100101001010001101101111110011001 +
b111111001111101010101101101110010 2
1%
#28600
0%
b1100 (
#28700
b1 6
b1010010100011011011111100110011 4
b1111111001111101010101101101110010010100101000110110111111001100 "
b1111111001111101010101101101110010010100101000110110111111001100 +
b111111100111110101010110110111001 2
b10111 7
1%
#28800
0%
b1101 (
#28900
b10 6
b1 5
b10110 7
b1111111100111110101010110110111001001010010100011011011111100110 "
b1111111100111110101010110110111001001010010100011011011111100110 +
b111111110011111010101011011011100 2
b100101001010001101101111110011001 4
1%
#29000
0%
b1110 (
#29100
b1010011011011010001111010011001010010100011011011111100110 "
b1010011011011010001111010011001010010100011011011111100110 +
b101001101101101000111101001 2
b10 5
1%
#29200
0%
b1111 (
#29300
b1 6
b10101 7
b101001101101101000111101001100101001010001101101111110011 "
b101001101101101000111101001100101001010001101101111110011 +
b10100110110110100011110100 2
b110010100101000110110111111001100 4
1%
#29400
0%
b10000 (
#29500
b10 6
b11001010010100011011011111100110 4
b10100110110110100011110100110010100101000110110111111001 "
b10100110110110100011110100110010100101000110110111111001 +
b1010011011011010001111010 2
b10100 7
b1 5
1%
#29600
0%
b10001 (
#29700
b10 5
b1111110101001010000111001011011010110010100101000110110111111001 "
b1111110101001010000111001011011010110010100101000110110111111001 +
b111111010100101000011100101101101 2
1%
#29800
0%
b10010 (
#29900
b1 6
b101100101001010001101101111110011 4
b1111111010100101000011100101101101011001010010100011011011111100 "
b1111111010100101000011100101101101011001010010100011011011111100 +
b111111101010010100001110010110110 2
b10011 7
1%
#30000
0%
b10011 (
