alu/alu_2.v
`timescale 10 ns / 1 ns

`define DATA_WIDTH 32

module alu(
	input  [`DATA_WIDTH - 1:0]  A,
	input  [`DATA_WIDTH - 1:0]  B,
	input  [              2:0]  ALUop,
	output                      Overflow,
	output                      CarryOut,
	output                      Zero,
	output [`DATA_WIDTH - 1:0]  Result
);
	// TODO: Please add your logic design here
	/* ALU opcode */
	parameter AND = 3'b000, OR = 3'b001, ADD = 3'b010, SUB = 3'b110, SLT = 3'b111;

	wire [`DATA_WIDTH - 1:0] A_switched, B_switched, res_sum, res_and, res_or;
	wire cin, cout;
	wire A_sign, B_sign, sum_sign;  /* signal bit */
	wire opAND, opOR, opADD, opSUB, opSLT;

	/*b32_adder ALU_adder (
		.A(A_switched), .B(B_switched), .cin(cin), .cout(cout), .S(res_sum)
	);*/
	assign { cout,res_sum } = A_switched + B_switched + cin;

	assign { opAND,opOR,opADD,opSUB,opSLT } = { ALUop == AND,ALUop == OR,ALUop == ADD,ALUop == SUB,ALUop == SLT };

	assign Zero = ~|Result;
	assign A_switched = (opSLT ? { ~A_sign,A[`DATA_WIDTH - 2:0] } : A);  /* use shift code when SLT */
	assign B_switched = (opSUB ? ~B : (opSLT ? ~{ ~B_sign,B[`DATA_WIDTH - 2:0] } : B));
	assign cin = (opSUB || opSLT ? 1'b1 : 1'b0);

	assign res_and = A & B;
	assign res_or = A | B;

	assign A_sign = A[`DATA_WIDTH - 1];
	assign B_sign = B[`DATA_WIDTH - 1];
	assign sum_sign = res_sum[`DATA_WIDTH - 1];

	assign Overflow = (A_sign == B_switched[`DATA_WIDTH - 1] && A_sign != sum_sign);
	assign CarryOut = (opADD && cout) || (opSUB && ~cout);

	assign Result = (
		{`DATA_WIDTH{opAND}} & res_and |
		{`DATA_WIDTH{opOR}} & res_or |
		{`DATA_WIDTH{opADD || opSUB}} & res_sum |
		{`DATA_WIDTH{opSLT}} & { 31'd0,~cout }
	);
endmodule

/*module b32_adder(
	input	[`DATA_WIDTH - 1:0]	A,
	input	[`DATA_WIDTH - 1:0]	B,
	input						cin,
	output						cout,
	output	[`DATA_WIDTH - 1:0] S
);
	assign { cout,S } = A + B + cin;
endmodule*/

alu/alu_tb.v
`timescale 10 ns / 1 ns

`define DATA_WIDTH 32
`define RND32 {$random} % (33'd1 << 32)
module alu_test_g();
	reg  [`DATA_WIDTH - 1:0]  A;
	reg  [`DATA_WIDTH - 1:0]  B;
	reg  [              2:0]  ALUop;
	wire                      Overflow;
	wire                      CarryOut;
	wire                      Zero;
	wire [`DATA_WIDTH - 1:0]  Result;
	parameter AND = 3'b000, OR = 3'b001, ADD = 3'b010, SUB = 3'b110, SLT = 3'b111;
	integer i;

	alu alu_tm(A, B, ALUop, Overflow, CarryOut, Zero, Result);

	initial begin
		ALUop = AND;
		for (i = 0; i < 10; i = i + 1) begin
			A = `RND32;
			B = `RND32;
			#10;
		end

		ALUop = OR;
		for (i = 0; i < 10; i = i + 1) begin
			A = `RND32;
			B = `RND32;
			#10;
		end

		ALUop = ADD;
		for (i = 0; i < 10; i = i + 1) begin
			A = `RND32;
			B = `RND32;
			#10;
		end

		ALUop = SUB;
		for (i = 0; i < 10; i = i + 1) begin
			A = `RND32;
			B = `RND32;
			#10;
		end

		ALUop = SLT;
		for (i = 0; i < 10; i = i + 1) begin
			A = `RND32;
			B = `RND32;
			#10;
		end
		$finish;
	end

	/*initial
		#600 $finish;*/
	initial begin
		$dumpfile("alu.vcd");
		$dumpvars(0, alu_test_g);
	end
endmodule

alu/alu.vcd
$date
	Fri Mar 10 18:17:40 2023
$end
$version
	Icarus Verilog
$end
$timescale
	1ns
$end
$scope module alu_test_g $end
$var wire 1 ! Zero $end
$var wire 32 " Result [31:0] $end
$var wire 1 # Overflow $end
$var wire 1 $ CarryOut $end
$var parameter 3 % ADD $end
$var parameter 3 & AND $end
$var parameter 3 ' OR $end
$var parameter 3 ( SLT $end
$var parameter 3 ) SUB $end
$var reg 32 * A [31:0] $end
$var reg 3 + ALUop [2:0] $end
$var reg 32 , B [31:0] $end
$var integer 32 - i [31:0] $end
$scope module alu_tm $end
$var wire 32 . A [31:0] $end
$var wire 3 / ALUop [2:0] $end
$var wire 32 0 B [31:0] $end
$var wire 1 $ CarryOut $end
$var wire 1 # Overflow $end
$var wire 32 1 res_and [31:0] $end
$var wire 32 2 res_or [31:0] $end
$var wire 1 3 sum_sign $end
$var wire 32 4 res_sum [31:0] $end
$var wire 1 5 opSUB $end
$var wire 1 6 opSLT $end
$var wire 1 7 opOR $end
$var wire 1 8 opAND $end
$var wire 1 9 opADD $end
$var wire 1 : cout $end
$var wire 1 ; cin $end
$var wire 1 ! Zero $end
$var wire 32 < Result [31:0] $end
$var wire 32 = B_switched [31:0] $end
$var wire 1 > B_sign $end
$var wire 32 ? A_switched [31:0] $end
$var wire 1 @ A_sign $end
$var parameter 3 A ADD $end
$var parameter 3 B AND $end
$var parameter 3 C OR $end
$var parameter 3 D SLT $end
$var parameter 3 E SUB $end
$upscope $end
$upscope $end
$enddefinitions $end
$comment Show the parameter values. $end
$dumpall
b110 E
b111 D
b1 C
b0 B
b10 A
b110 )
b111 (
b1 '
b0 &
b10 %
$end
#0
$dumpvars
0@
b10010000101010011010100100100 ?
1>
b11000000100010010101111010000001 =
b10001010000000000 <
0;
0:
09
18
07
06
05
b11010010100111101001001110100101 4
13
b11010010100111010111111110100101 2
b10001010000000000 1
b11000000100010010101111010000001 0
b0 /
b10010000101010011010100100100 .
b0 -
b11000000100010010101111010000001 ,
b0 +
b10010000101010011010100100100 *
0$
0#
b10001010000000000 "
0!
$end
#100
1#
03
b10110001111100000101011001100011 =
b10000000100000000101011000000001 "
b10000000100000000101011000000001 <
b110110011101010010110001101100 4
1:
b10000000100000000101011000000001 1
b10110101111101001101011001101011 2
b10000100100001001101011000001001 ?
1@
b10110001111100000101011001100011 ,
b10110001111100000101011001100011 0
b10000100100001001101011000001001 *
b10000100100001001101011000001001 .
b1 -
#200
03
0#
b1000110110111111001100110001101 =
b110100110010001100100001101 "
b110100110010001100100001101 <
b1001101100110010001010010011010 4
0:
0>
b110100110010001100100001101 1
b1000110111111111111101110001101 2
b110101110010111101100001101 ?
0@
b1000110110111111001100110001101 ,
b1000110110111111001100110001101 0
b110101110010111101100001101 *
b110101110010111101100001101 .
b10 -
#300
1#
1:
03
b10001001001101110101001000010010 =
b10000000000000100000000000000000 "
b10000000000000100000000000000000 <
b111011111110011101011001110111 4
1>
b10000000000000100000000000000000 1
b10111011111101111101011001110111 2
b10110010110000101000010001100101 ?
1@
b10001001001101110101001000010010 ,
b10001001001101110101001000010010 0
b10110010110000101000010001100101 *
b10110010110000101000010001100101 .
b11 -
#400
03
0#
b110110101111100110100001101 =
b110100111100000100000001 "
b110100111100000100000001 <
b111110010111011000000001110 4
0:
0>
b110100111100000100000001 1
b110111101111110111100001101 2
b111100111110001100000001 ?
0@
b110110101111100110100001101 ,
b110110101111100110100001101 0
b111100111110001100000001 *
b111100111110001100000001 .
b100 -
#500
b11110100011011100110100111101 =
b11010000000011100000100110100 "
b11010000000011100000100110100 <
b1011001101100011011111010110011 4
b11010000000011100000100110100 1
b111111101011111111110101111111 2
b111011001000111111000101110110 ?
b11110100011011100110100111101 ,
b11110100011011100110100111101 0
b111011001000111111000101110110 *
b111011001000111111000101110110 .
b101 -
#600
1#
13
b1000110001011011111011110001100 =
b1000110000001000101011110001100 "
b1000110000001000101011110001100 <
b10111101000000100100111101111001 4
b1000110000001000101011110001100 1
b1110110111111011111011111101101 2
b1110110110101000101011111101101 ?
b1000110001011011111011110001100 ,
b1000110001011011111011110001100 0
b1110110110101000101011111101101 *
b1110110110101000101011111101101 .
b110 -
#700
0#
03
1:
b11100011001101110010010011000110 =
b1100000001101010010000011000000 "
b1100000001101010010000011000000 <
b1100000001101010000111010111111 4
1>
b1100000001101010010000011000000 1
b11111111111111111110110111111111 2
b1111100111111011110100111111001 ?
b11100011001101110010010011000110 ,
b11100011001101110010010011000110 0
b1111100111111011110100111111001 *
b1111100111111011110100111111001 .
b111 -
#800
13
0#
b11010101000100111101001010101010 =
b11000000000100111000000010000000 "
b11000000000100111000000010000000 <
b10111000000010110101011101101111 4
b11000000000100111000000010000000 1
b11110111111101111101011011101111 2
b11100010111101111000010011000101 ?
1@
b11010101000100111101001010101010 ,
b11010101000100111101001010101010 0
b11100010111101111000010011000101 *
b11100010111101111000010011000101 .
b1000 -
#900
03
b10111011110100100111001001110111 =
b110010100000100111001001100101 "
b110010100000100111001001100101 <
b101110100000100110101001011100 4
b110010100000100111001001100101 1
b11111011111111111111011111110111 2
b1110010101011111111011111100101 ?
0@
b10111011110100100111001001110111 ,
b10111011110100100111001001110111 0
b1110010101011111111011111100101 *
b1110010101011111111011111100101 .
b1001 -
#1000
13
0:
0#
b1000111111011001101101110001111 =
b11010001000111111011000110100001 4
b11001111111111101101111110011111 "
b11001111111111101101111110011111 <
0>
b1001000001101001000000010 1
b11001111111111101101111110011111 2
b10001001001100101101011000010010 ?
1@
08
17
b1000111111011001101101110001111 ,
b1000111111011001101101110001111 0
b10001001001100101101011000010010 *
b10001001001100101101011000010010 .
b1 +
b1 /
b0 -
#1100
03
1:
b11111111011101101111111111111110 "
b11111111011101101111111111111110 <
0#
b11100111011101101001011011001110 =
b1100000101001110000000011000000 4
1>
b1100001001100000000000011000010 1
b11111111011101101111111111111110 2
b1111001001100000110100111110010 ?
0@
b11100111011101101001011011001110 ,
b11100111011101101001011011001110 0
b1111001001100000110100111110010 *
b1111001001100000110100111110010 .
b1 -
#1200
b11110110110010100111111011101101 "
b11110110110010100111111011101101 <
13
0#
b11100010110010100100111011000101 =
b11010110110010101100100110101101 4
b11100000000000000100101011000000 1
b11110110110010100111111011101101 2
b11110100000000000111101011101000 ?
1@
b11100010110010100100111011000101 ,
b11100010110010100100111011000101 0
b11110100000000000111101011101000 *
b11110100000000000111101011101000 .
b10 -
#1300
b11111110110111100110100111111101 "
b11111110110111100110100111111101 <
03
b11011110100011100010100010111101 =
b1100111001100111001000011001 4
b1110000010000000100000011100 1
b11111110110111100110100111111101 2
b101110010110000100100101011100 ?
0@
b11011110100011100010100010111101 ,
b11011110100011100010100010111101 0
b101110010110000100100101011100 *
b101110010110000100100101011100 .
b11 -
#1400
b10110110101011110111111001101101 "
b10110110101011110111111001101101 <
1#
b10110010101001110010011001100101 =
b1001001010100100111111010010010 4
b10010010101000110000000000100101 1
b10110110101011110111111001101101 2
b10010110101010110101100000101101 ?
1@
b10110010101001110010011001100101 ,
b10110010101001110010011001100101 0
b10010110101010110101100000101101 *
b10010110101010110101100000101101 .
b100 -
#1500
0#
13
0:
b10110101111111111110011101101011 "
b10110101111111111110011101101011 <
b101011100111000011100001010 =
b10110111011000101110100101101101 4
0>
b1011000110000001000000010 1
b10110101111111111110011101101011 2
b10110001111011110110001001100011 ?
b101011100111000011100001010 ,
b101011100111000011100001010 0
b10110001111011110110001001100011 *
b10110001111011110110001001100011 .
b101 -
#1600
b11010000011111110010001110100000 "
b11010000011111110010001110100000 <
b10000011001000010000100100000 =
b11010000100111110100001110100000 4
b1000000010000000000000 1
b11010000011111110010001110100000 2
b11000000001110110010001010000000 ?
b10000011001000010000100100000 ,
b10000011001000010000100100000 0
b11000000001110110010001010000000 *
b11000000001110110010001010000000 .
b110 -
#1700
1:
b11011111111111001100110110111111 "
b11011111111111001100110110111111 <
03
0#
b11001110110011001100110010011101 =
b100100010001010001001001000111 4
1>
b1000100010010000100010010001000 1
b11011111111111001100110110111111 2
b1010101011110000100010110101010 ?
0@
b11001110110011001100110010011101 ,
b11001110110011001100110010011101 0
b1010101011110000100010110101010 *
b1010101011110000100010110101010 .
b111 -
#1800
b11001011101000111011111010010111 "
b11001011101000111011111010010111 <
03
1#
b10001001100000111011100000010011 =
b1010100101000111111011010101001 4
b10001001000000000011100000010010 1
b11001011101000111011111010010111 2
b11001011001000000011111010010110 ?
1@
b10001001100000111011100000010011 ,
b10001001100000111011100000010011 0
b11001011001000000011111010010110 *
b11001011001000000011111010010110 .
b1000 -
#1900
b10101111101111111111111001011111 "
b10101111101111111111111001011111 <
b10101001101001111101011001010011 =
b110000011001000000111001100000 4
b10000000101001000001000000000001 1
b10101111101111111111111001011111 2
b10000110101111000011100000001101 ?
b10101001101001111101011001010011 ,
b10101001101001111101011001010011 0
b10000110101111000011100000001101 *
b10000110101111000011100000001101 .
b1001 -
#2000
03
0#
0!
b100000010001100000100001000000 "
b100000010001100000100001000000 <
1$
b11101010101001100010101011010101 =
b100000010001100000100001000000 4
1:
b100000100001100000100001000001 1
b11111111101111111111111111111111 2
b110101100111111101110101101011 ?
0@
07
19
b11101010101001100010101011010101 ,
b11101010101001100010101011010101 0
b110101100111111101110101101011 *
b110101100111111101110101101011 .
b10 +
b10 /
b0 -
#2100
b1011000011011011000100010110000 "
b1011000011011011000100010110000 <
1#
b11010111010101100011111010101110 =
b1011000011011011000100010110000 4
b10000001000101100000101000000010 1
b11010111010101110111111010101110 2
b10000001000101110100101000000010 ?
1@
b11010111010101100011111010101110 ,
b11010111010101100011111010101110 0
b10000001000101110100101000000010 *
b10000001000101110100101000000010 .
b1 -
#2200
b11110110110001010101101111101100 "
b11110110110001010101101111101100 <
0$
13
0#
b11100111110001010111001011001111 =
b11110110110001010101101111101100 4
0:
b110110001010110000000001101 1
b11101111111111111111101111011111 2
b1110111111111110100100011101 ?
0@
b11100111110001010111001011001111 ,
b11100111110001010111001011001111 0
b1110111111111110100100011101 *
b1110111111111110100100011101 .
b10 -
#2300
b10110100011011010111000101101 "
b10110100011011010111000101101 <
03
b101000010010110010100001010 =
b10110100011011010111000101101 4
0>
b1000000000100000100000010 1
b10101100011010110110100101011 2
b10001100001000100100100100011 ?
b101000010010110010100001010 ,
b101000010010110010100001010 0
b10001100001000100100100100011 *
b10001100001000100100100100011 .
b11 -
#2400
1$
b10000011101001000101011100000110 "
b10000011101001000101011100000110 <
1:
13
b10011110001100010100110000111100 =
b10000011101001000101011100000110 4
1>
b10000100001100010000100000001000 1
b11111111011100110100111011111110 2
b11100101011100110000101011001010 ?
1@
b10011110001100010100110000111100 ,
b10011110001100010100110000111100 0
b11100101011100110000101011001010 *
b11100101011100110000101011001010 .
b100 -
#2500
1#
0$
b10111110100101110001111101111100 "
b10111110100101110001111101111100 <
0:
13
b1000101001011100110000110001010 =
b10111110100101110001111101111100 4
0>
b1000001001010000010000110000010 1
b1111101011011101111110111111010 2
b1111001011010001011110111110010 ?
0@
b1000101001011100110000110001010 ,
b1000101001011100110000110001010 0
b1111001011010001011110111110010 *
b1111001011010001011110111110010 .
b101 -
#2600
1$
0#
b1101000011111110100000011001 "
b1101000011111110100000011001 <
1:
03
b11101100010010110011010011011000 =
b1101000011111110100000011001 4
1>
b100000010000000011000001000000 1
b11101100110011111011011111011001 2
b100000110001001011001101000001 ?
b11101100010010110011010011011000 ,
b11101100010010110011010011011000 0
b100000110001001011001101000001 *
b100000110001001011001101000001 .
b110 -
#2700
b101010110000011000000001 "
b101010110000011000000001 <
b11000100100010100001001010001001 =
b101010110000011000000001 4
b100000000000001001000001000 1
b11111100101010101111001111111001 2
b111100001000001111001101111000 ?
b11000100100010100001001010001001 ,
b11000100100010100001001010001001 0
b111100001000001111001101111000 *
b111100001000001111001101111000 .
b111 -
#2800
1#
0$
b11010000110001110111001110100001 "
b11010000110001110111001110100001 <
13
0:
b1011011000000100110010110110110 =
b11010000110001110111001110100001 4
0>
b1010001000000000000010110100010 1
b1111111110001110110110111111111 2
b1110101110001010000110111101011 ?
b1011011000000100110010110110110 ,
b1011011000000100110010110110110 0
b1110101110001010000110111101011 *
b1110101110001010000110111101011 .
b1000 -
#2900
b10111010011000010000110101110100 "
b10111010011000010000110101110100 <
b1010111000101010001001110101110 =
b10111010011000010000110101110100 4
b1000011000000010001000110000110 1
b1110111010111111111101111101110 2
b1100011010010111111100111000110 ?
b1010111000101010001001110101110 ,
b1010111000101010001001110101110 0
b1100011010010111111100111000110 *
b1100011010010111111100111000110 .
b1001 -
#3000
b11001001011001010010010110010010 "
b11001001011001010010010110010010 <
0#
0$
1;
b11001001011001010010010110010010 4
1:
b11101010111100000010001011010101 =
b10100000001010000000000101000 1
b11011111011111111101111110111110 2
b11011110011101010000001010111100 ?
1@
09
15
b10101000011111101110100101010 ,
b10101000011111101110100101010 0
b11011110011101010000001010111100 *
b11011110011101010000001010111100 .
b110 +
b110 /
b0 -
#3100
1$
b11001101001111111101101110011010 "
b11001101001111111101101110011010 <
0:
13
b1000111011010000100000110001110 =
b11001101001111111101101110011010 4
1>
b10000000100101111001101000000001 1
b10111101110101111011111001111011 2
b10000101110101111001101000001011 ?
b10111000100101111011111001110001 ,
b10111000100101111011111001110001 0
b10000101110101111001101000001011 *
b10000101110101111001101000001011 .
b1 -
#3200
0$
b11010111111111110110000110110 "
b11010111111111110110000110110 <
03
1:
0#
b11011000000011011010101010110000 =
b11010111111111110110000110110 4
0>
b10111100100100000100000101 1
b1100111111100100101010111001111 2
b1000010111100100100000110000101 ?
0@
b100111111100100101010101001111 ,
b100111111100100101010101001111 0
b1000010111100100100000110000101 *
b1000010111100100100000110000101 .
b10 -
#3300
b10000000110001100010110100000001 "
b10000000110001100010110100000001 <
13
0#
b11100010111110011100110011000101 =
b10000000110001100010110100000001 4
b11101000001000010000000111010 1
b10011101110011100111001100111011 2
b10011101110011000110000000111011 ?
1@
b11101000001100011001100111010 ,
b11101000001100011001100111010 0
b10011101110011000110000000111011 *
b10011101110011000110000000111011 .
b11 -
#3400
b10110100011110001110011101101001 "
b10110100011110001110011101101001 <
b11110101010101011011010011101010 =
b10110100011110001110011101101001 4
b1010001000100000001000010100 1
b10111111101010110111101101111111 2
b10111111001000110011001001111110 ?
b1010101010100100101100010101 ,
b1010101010100100101100010101 0
b10111111001000110011001001111110 *
b10111111001000110011001001111110 .
b100 -
#3500
b1100001111010101000000011000 "
b1100001111010101000000011000 <
03
b10010011011000111011010000100110 =
b1100001111010101000000011000 4
b1101000100110000000101111010001 1
b1111100110111011101101111111001 2
b1111000110110011001101111110001 ?
0@
b1101100100111000100101111011001 ,
b1101100100111000100101111011001 0
b1111000110110011001101111110001 *
b1111000110110011001101111110001 .
b101 -
#3600
b1010111011010000110000010110 "
b1010111011010000110000010110 <
0$
03
b11011001110010100000010010110011 =
b1010111011010000110000010110 4
1:
b100000001000010000001101000000 1
b110111001101111111111101101110 2
b110001001000110000011101100010 ?
b100110001101011111101101001100 ,
b100110001101011111101101001100 0
b110001001000110000011101100010 *
b110001001000110000011101100010 .
b110 -
#3700
b111111001111011010000010000 "
b111111001111011010000010000 <
b10111000010001100101111001110000 =
b111111001111011010000010000 4
b1000111101000010000000110001111 1
b1001111101110011111010110011111 2
b1001111101000010101010110011111 ?
b1000111101110011010000110001111 ,
b1000111101110011010000110001111 0
b1001111101000010101010110011111 *
b1001111101000010101010110011111 .
b111 -
#3800
1$
1#
b10100000101000000100100101000001 "
b10100000101000000100100101000001 <
13
0:
b100100001100101001111101001000 =
b10100000101000000100100101000001 4
1>
b1011000010011010010000010110000 1
b11111111111011011110100111111111 2
b1111100011011011010100111111000 ?
b11011011110011010110000010110111 ,
b11011011110011010110000010110111 0
b1111100011011011010100111111000 *
b1111100011011011010100111111000 .
b1000 -
#3900
0$
b100001010001101100001001000011 "
b100001010001101100001001000011 <
03
1:
0#
b1010001100000100110101110100011 =
b100001010001101100001001000011 4
b10001110010001000001010000011100 1
b11101111111111011101011011011111 2
b11001111110001000101011010011111 ?
1@
b10101110011111011001010001011100 ,
b10101110011111011001010001011100 0
b11001111110001000101011010011111 *
b11001111110001000101011010011111 .
b1001 -
#4000
0#
0!
b1 "
b1 <
03
b1101000111011011000100011010010 4
0:
b111011001000011100100001110110 =
0>
b100110010100000000000001001 1
b11101101110111111111011111011011 2
b101101110010111100000001011011 ?
05
16
b1000100110111100011011110001001 ,
b1000100110111100011011110001001 0
b10101101110010111100000001011011 *
b10101101110010111100000001011011 .
b111 +
b111 /
b0 -
#4100
13
b10010111110111001100000100101111 =
b10111100100010101111001101111001 4
b100100101011100011001001001001 ?
1>
b10100000001000100011001001000000 1
b11101100101011110011111011011001 2
b11101000001000110011111011010000 ,
b11101000001000110011111011010000 0
b10100100101011100011001001001001 *
b10100100101011100011001001001001 .
b1 -
#4200
1!
b0 "
b0 <
1#
b11010111001110000000001110101110 =
03
b1000011001101101100010010000110 4
1:
b1101011111111101100000011010111 ?
b10101000110001101100000001010001 1
b11101011111111111111110011010111 2
b10101000110001111111110001010001 ,
b10101000110001111111110001010001 0
b11101011111111101100000011010111 *
b11101011111111101100000011010111 .
b10 -
#4300
b1111001111000101000000011110011 =
03
b1000101000000111011000010001010 4
0#
b11001011001000010010111110010110 ?
0>
b10000000010010111100000100 1
b1001111001111010111111110011110 2
0@
b110000111010111111100001100 ,
b110000111010111111100001100 0
b1001011001000010010111110010110 *
b1001011001000010010111110010110 .
b11 -
#4400
0!
b1 "
b1 <
b11011101010000001001000110111 =
03
b1111100110101001110000011111010 4
0:
b1100001001011001100111011000010 ?
b1100000000001001100110011000000 1
b11100101011111111110111111001010 2
1@
b1100100010101111110110111001000 ,
b1100100010101111110110111001000 0
b11100001001011001100111011000010 *
b11100001001011001100111011000010 .
b100 -
#4500
13
b1100001000011010001001011000010 =
b10011100100011110110110100111010 4
b111011100000100101101001110111 ?
b11010100000100100100000110101 1
b10111111111100101111111101111111 2
b11110111100101110110100111101 ,
b11110111100101110110100111101 0
b10111011100000100101101001110111 *
b10111011100000100101101001110111 .
b101 -
#4600
1!
b0 "
b0 <
03
1:
b11000000111110101111111110000001 =
b1001010000001111101101010010100 4
0#
b10001001000011001101101100010010 ?
1>
b1001000001000000000000010010 1
b10111111000011011101101101111110 2
0@
b10111111000001010000000001111110 ,
b10111111000001010000000001111110 0
b1001000011001101101100010010 *
b1001000011001101101100010010 .
b110 -
#4700
b1100011001001100001100011000110 =
b11010000010111001101000110100 4
b10110110111001011000000101101101 ?
0>
b10100110000011000000100101001 1
b111110111111011110011101111101 2
b11100110110011110011100111001 ,
b11100110110011110011100111001 0
b110110111001011000000101101101 *
b110110111001011000000101101101 .
b111 -
#4800
1!
b0 "
b0 <
0#
b10010110000101000000100100101100 =
03
b100101111001101001100001001100 4
1:
b10001111110100101000111100011111 ?
1>
b1001110000101000011000010011 1
b11101111111110111111111111011111 2
b11101001111010111111011011010011 ,
b11101001111010111111011011010011 0
b1111110100101000111100011111 *
b1111110100101000111100011111 .
b1000 -
#4900
13
b11000011111010110111011110000111 =
b10000110110001001010011100001101 4
b11000010110110010010111110000101 ?
b100000000100000000000 1
b11111110110111011010111111111101 2
b10111100000101001000100001111000 ,
b10111100000101001000100001111000 0
b1000010110110010010111110000101 *
b1000010110110010010111110000101 .
b1001 -
#5000
b1010 -
