simple_cpu/reg_file.v
`timescale 10 ns / 1 ns

`define DATA_WIDTH 32
`define ADDR_WIDTH 5

module reg_file(
	input                       clk,
	input  [`ADDR_WIDTH - 1:0]  waddr,
	input  [`ADDR_WIDTH - 1:0]  raddr1,
	input  [`ADDR_WIDTH - 1:0]  raddr2,
	input                       wen,
	input  [`DATA_WIDTH - 1:0]  wdata,
	output [`DATA_WIDTH - 1:0]  rdata1,
	output [`DATA_WIDTH - 1:0]  rdata2
);

	// TODO: Please add your logic design here
	
	reg [`DATA_WIDTH - 1:0] rf [31:0];
	
	always @ (posedge clk) begin
		if (wen != 0 && waddr != 0)
			rf[waddr] <= wdata;
	end

	assign rdata1 = (raddr1 == 0 ? 32'd0 : rf[raddr1]);
	assign rdata2 = (raddr2 == 0 ? 32'd0 : rf[raddr2]);

endmodule

reg_file/rf_tb.v
`timescale 10 ns / 1 ns

`define DATA_WIDTH 32
`define ADDR_WIDTH 5

module rf_tb();
    reg clk;
    reg [`ADDR_WIDTH - 1:0] waddr, raddr1, raddr2;
    reg [`DATA_WIDTH - 1:0] wdata;
    wire [`DATA_WIDTH - 1:0] rdata1, rdata2;
    integer i;

    reg_file rf1(clk, waddr, raddr1, raddr2, 1'b1, wdata, rdata1, rdata2);

    initial begin
        clk = 0;

        for (i = 0; i < 32; i = i + 1) begin
            waddr = i;
            wdata = i;
            #5
            clk = 1;
            #25
            clk = 0;
        end
    end

    initial begin
        wait (i >= 32);
        forever #20 begin
            raddr1 = {$random} % 32;
            raddr2 = {$random} % 32;
        end
    end

    initial begin
        #1600
        $finish;
    end

    initial begin
        $dumpfile("reg_file.vcd");
        $dumpvars(0, rf_tb);
    end

endmodule

reg_file/reg_file.vcd
$date
	Fri Mar 10 16:39:41 2023
$end
$version
	Icarus Verilog
$end
$timescale
	1ns
$end
$scope module rf_tb $end
$var wire 32 ! rdata2 [31:0] $end
$var wire 32 " rdata1 [31:0] $end
$var reg 1 # clk $end
$var reg 5 $ raddr1 [4:0] $end
$var reg 5 % raddr2 [4:0] $end
$var reg 5 & waddr [4:0] $end
$var reg 32 ' wdata [31:0] $end
$var integer 32 ( i [31:0] $end
$scope module rf1 $end
$var wire 1 # clk $end
$var wire 5 ) raddr1 [4:0] $end
$var wire 5 * raddr2 [4:0] $end
$var wire 5 + waddr [4:0] $end
$var wire 32 , wdata [31:0] $end
$var wire 1 - wen $end
$var wire 32 . rdata2 [31:0] $end
$var wire 32 / rdata1 [31:0] $end
$upscope $end
$upscope $end
$enddefinitions $end
$comment Show the parameter values. $end
$dumpall
$end
#0
$dumpvars
bx /
bx .
1-
b0 ,
b0 +
bx *
bx )
b0 (
b0 '
b0 &
bx %
bx $
0#
bx "
bx !
$end
#50
1#
#300
b1 '
b1 ,
b1 &
b1 +
b1 (
0#
#350
1#
#600
b10 '
b10 ,
b10 &
b10 +
b10 (
0#
#650
1#
#900
b11 '
b11 ,
b11 &
b11 +
b11 (
0#
#950
1#
#1200
b100 '
b100 ,
b100 &
b100 +
b100 (
0#
#1250
1#
#1500
b101 '
b101 ,
b101 &
b101 +
b101 (
0#
#1550
1#
#1800
b110 '
b110 ,
b110 &
b110 +
b110 (
0#
#1850
1#
#2100
b111 '
b111 ,
b111 &
b111 +
b111 (
0#
#2150
1#
#2400
b1000 '
b1000 ,
b1000 &
b1000 +
b1000 (
0#
#2450
1#
#2700
b1001 '
b1001 ,
b1001 &
b1001 +
b1001 (
0#
#2750
1#
#3000
b1010 '
b1010 ,
b1010 &
b1010 +
b1010 (
0#
#3050
1#
#3300
b1011 '
b1011 ,
b1011 &
b1011 +
b1011 (
0#
#3350
1#
#3600
b1100 '
b1100 ,
b1100 &
b1100 +
b1100 (
0#
#3650
1#
#3900
b1101 '
b1101 ,
b1101 &
b1101 +
b1101 (
0#
#3950
1#
#4200
b1110 '
b1110 ,
b1110 &
b1110 +
b1110 (
0#
#4250
1#
#4500
b1111 '
b1111 ,
b1111 &
b1111 +
b1111 (
0#
#4550
1#
#4800
b10000 '
b10000 ,
b10000 &
b10000 +
b10000 (
0#
#4850
1#
#5100
b10001 '
b10001 ,
b10001 &
b10001 +
b10001 (
0#
#5150
1#
#5400
b10010 '
b10010 ,
b10010 &
b10010 +
b10010 (
0#
#5450
1#
#5700
b10011 '
b10011 ,
b10011 &
b10011 +
b10011 (
0#
#5750
1#
#6000
b10100 '
b10100 ,
b10100 &
b10100 +
b10100 (
0#
#6050
1#
#6300
b10101 '
b10101 ,
b10101 &
b10101 +
b10101 (
0#
#6350
1#
#6600
b10110 '
b10110 ,
b10110 &
b10110 +
b10110 (
0#
#6650
1#
#6900
b10111 '
b10111 ,
b10111 &
b10111 +
b10111 (
0#
#6950
1#
#7200
b11000 '
b11000 ,
b11000 &
b11000 +
b11000 (
0#
#7250
1#
#7500
b11001 '
b11001 ,
b11001 &
b11001 +
b11001 (
0#
#7550
1#
#7800
b11010 '
b11010 ,
b11010 &
b11010 +
b11010 (
0#
#7850
1#
#8100
b11011 '
b11011 ,
b11011 &
b11011 +
b11011 (
0#
#8150
1#
#8400
b11100 '
b11100 ,
b11100 &
b11100 +
b11100 (
0#
#8450
1#
#8700
b11101 '
b11101 ,
b11101 &
b11101 +
b11101 (
0#
#8750
1#
#9000
b11110 '
b11110 ,
b11110 &
b11110 +
b11110 (
0#
#9050
1#
#9300
b11111 '
b11111 ,
b11111 &
b11111 +
b11111 (
0#
#9350
1#
#9600
b100000 (
0#
#9800
b1 !
b1 .
b100 "
b100 /
b1 %
b1 *
b100 $
b100 )
#10000
b11 !
b11 .
b1001 "
b1001 /
b11 %
b11 *
b1001 $
b1001 )
#10200
b1101 !
b1101 .
b1101 "
b1101 /
b1101 %
b1101 *
b1101 $
b1101 )
#10400
b10010 !
b10010 .
b101 "
b101 /
b10010 %
b10010 *
b101 $
b101 )
#10600
b1101 !
b1101 .
b1 "
b1 /
b1101 %
b1101 *
b1 $
b1 )
#10800
b11101 !
b11101 .
b10110 "
b10110 /
b11101 %
b11101 *
b10110 $
b10110 )
#11000
b1100 !
b1100 .
b1101 "
b1101 /
b1100 %
b1100 *
b1101 $
b1101 )
#11200
b110 !
b110 .
b11001 "
b11001 /
b110 %
b110 *
b11001 $
b11001 )
#11400
b1010 !
b1010 .
b101 "
b101 /
b1010 %
b1010 *
b101 $
b101 )
#11600
b10111 !
b10111 .
b10111 %
b10111 *
#11800
b1111 !
b1111 .
b10010 "
b10010 /
b1111 %
b1111 *
b10010 $
b10010 )
#12000
b1110 !
b1110 .
b1110 %
b1110 *
#12200
b101 !
b101 .
b1000 "
b1000 /
b101 %
b101 *
b1000 $
b1000 )
#12400
b11101 !
b11101 .
b11100 "
b11100 /
b11101 %
b11101 *
b11100 $
b11100 )
#12600
b101 !
b101 .
b1101 "
b1101 /
b101 %
b101 *
b1101 $
b1101 )
#12800
b1010 !
b1010 .
b11 "
b11 /
b1010 %
b1010 *
b11 $
b11 )
#13000
b0 !
b0 .
b0 "
b0 /
b0 %
b0 *
b0 $
b0 )
#13200
b11101 !
b11101 .
b1010 "
b1010 /
b11101 %
b11101 *
b1010 $
b1010 )
#13400
b10011 !
b10011 .
b10110 "
b10110 /
b10011 %
b10011 *
b10110 $
b10110 )
#13600
b1101 "
b1101 /
b1101 $
b1101 )
#13800
b10101 !
b10101 .
b1011 "
b1011 /
b10101 %
b10101 *
b1011 $
b1011 )
#14000
b1110 !
b1110 .
b10 "
b10 /
b1110 %
b1110 *
b10 $
b10 )
#14200
b1111 !
b1111 .
b11101 "
b11101 /
b1111 %
b1111 *
b11101 $
b11101 )
#14400
b1010 !
b1010 .
b11 "
b11 /
b1010 %
b1010 *
b11 $
b11 )
#14600
b11100 !
b11100 .
b1010 "
b1010 /
b11100 %
b11100 *
b1010 $
b1010 )
#14800
b1010 !
b1010 .
b10010 "
b10010 /
b1010 %
b1010 *
b10010 $
b10010 )
#15000
b11000 !
b11000 .
b1 "
b1 /
b11000 %
b11000 *
b1 $
b1 )
#15200
b1001 !
b1001 .
b11000 "
b11000 /
b1001 %
b1001 *
b11000 $
b11000 )
#15400
b10110 !
b10110 .
b1011 "
b1011 /
b10110 %
b10110 *
b1011 $
b1011 )
#15600
b1110 !
b1110 .
b110 "
b110 /
b1110 %
b1110 *
b110 $
b110 )
#15800
b1010 !
b1010 .
b11100 "
b11100 /
b1010 %
b1010 *
b11100 $
b11100 )
